[
	{
		"title": "",
		"subtitle": "Реакція — це миттєва відповідь на спрацювання певної умови, яка може відбуватися як у ваш, так і в чужий хід.",
		"rules": [
			{
				"title": "Спровокована атака",
				"icon": "backstab",
				"subtitle": "Спровокована атака по противнику, що залишає вашу досяжність",
				"reference": "КГ, стор. 195",
				"description": "<p>Ви можете здійснити спровоковану атаку, якщо ворожа істота, яку ви бачите, залишає вашу досяжність.</p><p>Для цього ви реакцією здійснюєте одну рукопашну атаку по істоті, що спровокувала атаку.</p><p>Ця атака перериває переміщення істоти, що спровокувала атаку, відбуваючись саме перед тим, як вона залишить межі вашої досяжності.</p><p>Ви можете уникнути спровокованої атаки, здійснивши дію Відхід. Ви також не провокуєте атаки, якщо телепортуєтеся, або хтось (щось) переміщує вас, не витрачаючи вашого переміщення, дії та реакції.</p><p>Спровокована атака не отримує додаткової атаки (здатність воїна), оскільки не є дією Атака.</p>"
			},
			{
				"title": "Підготовлена атака",
				"icon": "empty-hourglass",
				"subtitle": "Здійснити атаку реакцією як частину дії Підготовки",
				"reference": "КГ, стор. 193",
				"description": "<p>Умова: при досягненні умов дії Підготовки.</p>"
			},
			{
				"title": "Накладання закляття",
				"icon": "magic-swirl",
				"subtitle": "Накласти закляття з часом накладання в 1 реакцію",
				"reference": "КГ, стор. 192",
				"description": "<p>Умова: залежить від закляття.</p><p>Дивіться основну дію <i>Накладання закляття</i> для подробиць.</p>"
			}
		]
	}
]
